MANIFEST.in
PKG-INFO
README.rst
setup.py
version
k2_compose/__init__.py
k2_compose/k2unittest.py
k2_compose/run.py
k2_compose.egg-info/PKG-INFO
k2_compose.egg-info/SOURCES.txt
k2_compose.egg-info/dependency_links.txt
k2_compose.egg-info/entry_points.txt
k2_compose.egg-info/requires.txt
k2_compose.egg-info/top_level.txt
k2_compose/agent/__init__.py
k2_compose/agent/grafana.py
k2_compose/agent/opentsdb.py
k2_compose/common/__init__.py
k2_compose/common/common.py
k2_compose/common/globalVar.py
k2_compose/compose_file/__init__.py
k2_compose/compose_file/compose_file.py
k2_compose/container/__init__.py
k2_compose/container/container.py
k2_compose/host/__init__.py
k2_compose/host/host.py
k2_compose/image/__init__.py
k2_compose/image/image_history.py
k2_compose/image/image_show.py
k2_compose/k2cutils/__init__.py
k2_compose/k2cutils/basenode.py
k2_compose/k2cutils/class_utils.py
k2_compose/k2cutils/confirm_input.py
k2_compose/k2cutils/misc.py
k2_compose/k2cutils/toposort.py
k2_compose/service/__init__.py
k2_compose/service/service.py
tests/docker-compose.yml
tests/k2-compose.yml