Metadata-Version: 1.0
Name: k2-compose
Version: 0.2.0
Summary: K2Platform deployment tool
Home-page: https://github.com/Tsui89/k2-compose
Author: hippopo
Author-email: wch.c@qq.com
License: UNKNOWN
Platform: UNKNOWN
